README
setup.py
zabbixapi/__init__.py
zabbixapi/zabbix_api.py
zabbixapi/zabbix_session.py
zabbixapi.egg-info/PKG-INFO
zabbixapi.egg-info/SOURCES.txt
zabbixapi.egg-info/dependency_links.txt
zabbixapi.egg-info/pbr.json
zabbixapi.egg-info/top_level.txt